Metadata-Version: 2.1
Name: swagMerge
Version: 1.0.2
Summary: Combine multiple Swagger files into a single YAML file.
Home-page: https://gitlab.allence.cloud/commons-acp/python/swagmerge
Author: yacine.jlassi
Author-email: mohamedyacine.jlassi@allence-tunisie.com
License: UNKNOWN
Platform: UNKNOWN
